{"allContent":{"docusaurus-plugin-css-cascade-layers":{},"docusaurus-plugin-content-docs":{"default":{"loadedVersions":[{"versionName":"current","label":"Next","banner":null,"badge":false,"noIndex":false,"className":"docs-version-current","path":"/docs","tagsPath":"/docs/tags","editUrl":"https://github.com/Abhishek1998-cpu/Digitrix-documentation/tree/main/docs","isLast":true,"routePriority":-1,"sidebarFilePath":"/Users/abhverma18/Desktop/Sample-Projects/Digitrix-documentation/sidebars.ts","contentPath":"/Users/abhverma18/Desktop/Sample-Projects/Digitrix-documentation/docs","docs":[{"id":"api/authentication","title":"Authentication API","description":"API endpoints for user authentication and account management.","source":"@site/docs/api/authentication.md","sourceDirName":"api","slug":"/api/authentication","permalink":"/docs/api/authentication","draft":false,"unlisted":false,"editUrl":"https://github.com/Abhishek1998-cpu/Digitrix-documentation/tree/main/docs/api/authentication.md","tags":[],"version":"current","sidebarPosition":2,"frontMatter":{"sidebar_position":2},"sidebar":"tutorialSidebar","previous":{"title":"API Overview","permalink":"/docs/api/overview"},"next":{"title":"Post Management API","permalink":"/docs/api/posts"}},{"id":"api/overview","title":"API Overview","description":"The DulyPlan API provides programmatic access to the platform's features and data.","source":"@site/docs/api/overview.md","sourceDirName":"api","slug":"/api/overview","permalink":"/docs/api/overview","draft":false,"unlisted":false,"editUrl":"https://github.com/Abhishek1998-cpu/Digitrix-documentation/tree/main/docs/api/overview.md","tags":[],"version":"current","sidebarPosition":1,"frontMatter":{"sidebar_position":1},"sidebar":"tutorialSidebar","previous":{"title":"Strapi Webhook Configuration","permalink":"/docs/strapi/webhook-configuration"},"next":{"title":"Authentication API","permalink":"/docs/api/authentication"}},{"id":"api/posts","title":"Post Management API","description":"API endpoints for creating, managing, and scheduling posts.","source":"@site/docs/api/posts.md","sourceDirName":"api","slug":"/api/posts","permalink":"/docs/api/posts","draft":false,"unlisted":false,"editUrl":"https://github.com/Abhishek1998-cpu/Digitrix-documentation/tree/main/docs/api/posts.md","tags":[],"version":"current","sidebarPosition":3,"frontMatter":{"sidebar_position":3},"sidebar":"tutorialSidebar","previous":{"title":"Authentication API","permalink":"/docs/api/authentication"},"next":{"title":"Social Accounts API","permalink":"/docs/api/social-accounts"}},{"id":"api/social-accounts","title":"Social Accounts API","description":"API endpoints for managing social media account connections.","source":"@site/docs/api/social-accounts.md","sourceDirName":"api","slug":"/api/social-accounts","permalink":"/docs/api/social-accounts","draft":false,"unlisted":false,"editUrl":"https://github.com/Abhishek1998-cpu/Digitrix-documentation/tree/main/docs/api/social-accounts.md","tags":[],"version":"current","sidebarPosition":4,"frontMatter":{"sidebar_position":4},"sidebar":"tutorialSidebar","previous":{"title":"Post Management API","permalink":"/docs/api/posts"},"next":{"title":"Development Setup","permalink":"/docs/development/setup"}},{"id":"architecture/backend","title":"Backend Architecture","description":"This document describes the backend architecture of DulyPlan.","source":"@site/docs/architecture/backend.md","sourceDirName":"architecture","slug":"/architecture/backend","permalink":"/docs/architecture/backend","draft":false,"unlisted":false,"editUrl":"https://github.com/Abhishek1998-cpu/Digitrix-documentation/tree/main/docs/architecture/backend.md","tags":[],"version":"current","sidebarPosition":2,"frontMatter":{"sidebar_position":2},"sidebar":"tutorialSidebar","previous":{"title":"Architecture Overview","permalink":"/docs/architecture/overview"},"next":{"title":"Frontend Architecture","permalink":"/docs/architecture/frontend"}},{"id":"architecture/frontend","title":"Frontend Architecture","description":"This document describes the frontend architecture of DulyPlan.","source":"@site/docs/architecture/frontend.md","sourceDirName":"architecture","slug":"/architecture/frontend","permalink":"/docs/architecture/frontend","draft":false,"unlisted":false,"editUrl":"https://github.com/Abhishek1998-cpu/Digitrix-documentation/tree/main/docs/architecture/frontend.md","tags":[],"version":"current","sidebarPosition":3,"frontMatter":{"sidebar_position":3},"sidebar":"tutorialSidebar","previous":{"title":"Backend Architecture","permalink":"/docs/architecture/backend"},"next":{"title":"Strapi Integration Overview","permalink":"/docs/strapi/overview"}},{"id":"architecture/overview","title":"Architecture Overview","description":"This document provides a high-level overview of the DulyPlan system architecture.","source":"@site/docs/architecture/overview.md","sourceDirName":"architecture","slug":"/architecture/overview","permalink":"/docs/architecture/overview","draft":false,"unlisted":false,"editUrl":"https://github.com/Abhishek1998-cpu/Digitrix-documentation/tree/main/docs/architecture/overview.md","tags":[],"version":"current","sidebarPosition":1,"frontMatter":{"sidebar_position":1},"sidebar":"tutorialSidebar","previous":{"title":"Account Management","permalink":"/docs/user/account-management"},"next":{"title":"Backend Architecture","permalink":"/docs/architecture/backend"}},{"id":"development/code-structure","title":"Code Structure","description":"Understand the codebase structure and organization.","source":"@site/docs/development/code-structure.md","sourceDirName":"development","slug":"/development/code-structure","permalink":"/docs/development/code-structure","draft":false,"unlisted":false,"editUrl":"https://github.com/Abhishek1998-cpu/Digitrix-documentation/tree/main/docs/development/code-structure.md","tags":[],"version":"current","sidebarPosition":3,"frontMatter":{"sidebar_position":3},"sidebar":"tutorialSidebar","previous":{"title":"Development Workflow","permalink":"/docs/development/workflow"},"next":{"title":"Frequently Asked Questions","permalink":"/docs/faq"}},{"id":"development/setup","title":"Development Setup","description":"This guide will help you set up your development environment for DulyPlan.","source":"@site/docs/development/setup.md","sourceDirName":"development","slug":"/development/setup","permalink":"/docs/development/setup","draft":false,"unlisted":false,"editUrl":"https://github.com/Abhishek1998-cpu/Digitrix-documentation/tree/main/docs/development/setup.md","tags":[],"version":"current","sidebarPosition":1,"frontMatter":{"sidebar_position":1},"sidebar":"tutorialSidebar","previous":{"title":"Social Accounts API","permalink":"/docs/api/social-accounts"},"next":{"title":"Development Workflow","permalink":"/docs/development/workflow"}},{"id":"development/workflow","title":"Development Workflow","description":"Learn about the development workflow for contributing to DulyPlan.","source":"@site/docs/development/workflow.md","sourceDirName":"development","slug":"/development/workflow","permalink":"/docs/development/workflow","draft":false,"unlisted":false,"editUrl":"https://github.com/Abhishek1998-cpu/Digitrix-documentation/tree/main/docs/development/workflow.md","tags":[],"version":"current","sidebarPosition":2,"frontMatter":{"sidebar_position":2},"sidebar":"tutorialSidebar","previous":{"title":"Development Setup","permalink":"/docs/development/setup"},"next":{"title":"Code Structure","permalink":"/docs/development/code-structure"}},{"id":"faq","title":"Frequently Asked Questions","description":"Common questions and answers about DulyPlan.","source":"@site/docs/faq.md","sourceDirName":".","slug":"/faq","permalink":"/docs/faq","draft":false,"unlisted":false,"editUrl":"https://github.com/Abhishek1998-cpu/Digitrix-documentation/tree/main/docs/faq.md","tags":[],"version":"current","sidebarPosition":10,"frontMatter":{"sidebar_position":10},"sidebar":"tutorialSidebar","previous":{"title":"Code Structure","permalink":"/docs/development/code-structure"}},{"id":"features/creating-posts","title":"Creating Posts","description":"Learn how to create and publish posts on DulyPlan.","source":"@site/docs/features/creating-posts.md","sourceDirName":"features","slug":"/features/creating-posts","permalink":"/docs/features/creating-posts","draft":false,"unlisted":false,"editUrl":"https://github.com/Abhishek1998-cpu/Digitrix-documentation/tree/main/docs/features/creating-posts.md","tags":[],"version":"current","sidebarPosition":2,"frontMatter":{"sidebar_position":2},"sidebar":"tutorialSidebar","previous":{"title":"Social Media Accounts","permalink":"/docs/features/social-accounts"},"next":{"title":"Scheduling Posts","permalink":"/docs/features/scheduling"}},{"id":"features/post-editor","title":"Post Editor Features","description":"Advanced features available in the DulyPlan post editor.","source":"@site/docs/features/post-editor.md","sourceDirName":"features","slug":"/features/post-editor","permalink":"/docs/features/post-editor","draft":false,"unlisted":false,"editUrl":"https://github.com/Abhishek1998-cpu/Digitrix-documentation/tree/main/docs/features/post-editor.md","tags":[],"version":"current","sidebarPosition":4,"frontMatter":{"sidebar_position":4},"sidebar":"tutorialSidebar","previous":{"title":"Scheduling Posts","permalink":"/docs/features/scheduling"},"next":{"title":"User Management Overview","permalink":"/docs/user/overview"}},{"id":"features/scheduling","title":"Scheduling Posts","description":"Learn how to schedule posts for future publication.","source":"@site/docs/features/scheduling.md","sourceDirName":"features","slug":"/features/scheduling","permalink":"/docs/features/scheduling","draft":false,"unlisted":false,"editUrl":"https://github.com/Abhishek1998-cpu/Digitrix-documentation/tree/main/docs/features/scheduling.md","tags":[],"version":"current","sidebarPosition":3,"frontMatter":{"sidebar_position":3},"sidebar":"tutorialSidebar","previous":{"title":"Creating Posts","permalink":"/docs/features/creating-posts"},"next":{"title":"Post Editor Features","permalink":"/docs/features/post-editor"}},{"id":"features/social-accounts","title":"Social Media Accounts","description":"Manage your connected social media accounts in DulyPlan.","source":"@site/docs/features/social-accounts.md","sourceDirName":"features","slug":"/features/social-accounts","permalink":"/docs/features/social-accounts","draft":false,"unlisted":false,"editUrl":"https://github.com/Abhishek1998-cpu/Digitrix-documentation/tree/main/docs/features/social-accounts.md","tags":[],"version":"current","sidebarPosition":1,"frontMatter":{"sidebar_position":1},"sidebar":"tutorialSidebar","previous":{"title":"Welcome to DulyPlan Documentation","permalink":"/docs/intro"},"next":{"title":"Creating Posts","permalink":"/docs/features/creating-posts"}},{"id":"getting-started/account-setup","title":"Account Setup","description":"Learn how to create and set up your DulyPlan account.","source":"@site/docs/getting-started/account-setup.md","sourceDirName":"getting-started","slug":"/getting-started/account-setup","permalink":"/docs/getting-started/account-setup","draft":false,"unlisted":false,"editUrl":"https://github.com/Abhishek1998-cpu/Digitrix-documentation/tree/main/docs/getting-started/account-setup.md","tags":[],"version":"current","sidebarPosition":2,"frontMatter":{"sidebar_position":2},"sidebar":"tutorialSidebar","previous":{"title":"Getting Started with DulyPlan","permalink":"/docs/getting-started/overview"},"next":{"title":"Dashboard Overview","permalink":"/docs/getting-started/dashboard-overview"}},{"id":"getting-started/connecting-accounts","title":"Connecting Social Media Accounts","description":"Learn how to connect your social media accounts to DulyPlan.","source":"@site/docs/getting-started/connecting-accounts.md","sourceDirName":"getting-started","slug":"/getting-started/connecting-accounts","permalink":"/docs/getting-started/connecting-accounts","draft":false,"unlisted":false,"editUrl":"https://github.com/Abhishek1998-cpu/Digitrix-documentation/tree/main/docs/getting-started/connecting-accounts.md","tags":[],"version":"current","sidebarPosition":4,"frontMatter":{"sidebar_position":4},"sidebar":"tutorialSidebar","previous":{"title":"Dashboard Overview","permalink":"/docs/getting-started/dashboard-overview"},"next":{"title":"Welcome to DulyPlan Documentation","permalink":"/docs/intro"}},{"id":"getting-started/dashboard-overview","title":"Dashboard Overview","description":"Get familiar with the DulyPlan dashboard and its main features.","source":"@site/docs/getting-started/dashboard-overview.md","sourceDirName":"getting-started","slug":"/getting-started/dashboard-overview","permalink":"/docs/getting-started/dashboard-overview","draft":false,"unlisted":false,"editUrl":"https://github.com/Abhishek1998-cpu/Digitrix-documentation/tree/main/docs/getting-started/dashboard-overview.md","tags":[],"version":"current","sidebarPosition":3,"frontMatter":{"sidebar_position":3},"sidebar":"tutorialSidebar","previous":{"title":"Account Setup","permalink":"/docs/getting-started/account-setup"},"next":{"title":"Connecting Social Media Accounts","permalink":"/docs/getting-started/connecting-accounts"}},{"id":"getting-started/overview","title":"Getting Started with DulyPlan","description":"Welcome to DulyPlan! This guide will help you get started with the platform.","source":"@site/docs/getting-started/overview.md","sourceDirName":"getting-started","slug":"/getting-started/overview","permalink":"/docs/getting-started/overview","draft":false,"unlisted":false,"editUrl":"https://github.com/Abhishek1998-cpu/Digitrix-documentation/tree/main/docs/getting-started/overview.md","tags":[],"version":"current","sidebarPosition":1,"frontMatter":{"sidebar_position":1},"sidebar":"tutorialSidebar","next":{"title":"Account Setup","permalink":"/docs/getting-started/account-setup"}},{"id":"intro","title":"Welcome to DulyPlan Documentation","description":"Welcome to the official documentation for DulyPlan - a comprehensive social media management platform that helps you plan, schedule, and manage your social media presence across multiple platforms.","source":"@site/docs/intro.md","sourceDirName":".","slug":"/intro","permalink":"/docs/intro","draft":false,"unlisted":false,"editUrl":"https://github.com/Abhishek1998-cpu/Digitrix-documentation/tree/main/docs/intro.md","tags":[],"version":"current","sidebarPosition":1,"frontMatter":{"sidebar_position":1},"sidebar":"tutorialSidebar","previous":{"title":"Connecting Social Media Accounts","permalink":"/docs/getting-started/connecting-accounts"},"next":{"title":"Social Media Accounts","permalink":"/docs/features/social-accounts"}},{"id":"strapi/backend-integration","title":"Backend Strapi Integration","description":"Learn how the backend integrates with Strapi CMS.","source":"@site/docs/strapi/backend-integration.md","sourceDirName":"strapi","slug":"/strapi/backend-integration","permalink":"/docs/strapi/backend-integration","draft":false,"unlisted":false,"editUrl":"https://github.com/Abhishek1998-cpu/Digitrix-documentation/tree/main/docs/strapi/backend-integration.md","tags":[],"version":"current","sidebarPosition":2,"frontMatter":{"sidebar_position":2},"sidebar":"tutorialSidebar","previous":{"title":"Strapi Integration Overview","permalink":"/docs/strapi/overview"},"next":{"title":"Frontend Strapi Integration","permalink":"/docs/strapi/frontend-integration"}},{"id":"strapi/data-structure","title":"Strapi Data Structure","description":"Understand the structure of Strapi content data in DulyPlan.","source":"@site/docs/strapi/data-structure.md","sourceDirName":"strapi","slug":"/strapi/data-structure","permalink":"/docs/strapi/data-structure","draft":false,"unlisted":false,"editUrl":"https://github.com/Abhishek1998-cpu/Digitrix-documentation/tree/main/docs/strapi/data-structure.md","tags":[],"version":"current","sidebarPosition":4,"frontMatter":{"sidebar_position":4},"sidebar":"tutorialSidebar","previous":{"title":"Frontend Strapi Integration","permalink":"/docs/strapi/frontend-integration"},"next":{"title":"Strapi Usage Examples","permalink":"/docs/strapi/usage-examples"}},{"id":"strapi/frontend-integration","title":"Frontend Strapi Integration","description":"Learn how the frontend integrates with Strapi content.","source":"@site/docs/strapi/frontend-integration.md","sourceDirName":"strapi","slug":"/strapi/frontend-integration","permalink":"/docs/strapi/frontend-integration","draft":false,"unlisted":false,"editUrl":"https://github.com/Abhishek1998-cpu/Digitrix-documentation/tree/main/docs/strapi/frontend-integration.md","tags":[],"version":"current","sidebarPosition":3,"frontMatter":{"sidebar_position":3},"sidebar":"tutorialSidebar","previous":{"title":"Backend Strapi Integration","permalink":"/docs/strapi/backend-integration"},"next":{"title":"Strapi Data Structure","permalink":"/docs/strapi/data-structure"}},{"id":"strapi/overview","title":"Strapi Integration Overview","description":"Learn how DulyPlan integrates with Strapi CMS for content management.","source":"@site/docs/strapi/overview.md","sourceDirName":"strapi","slug":"/strapi/overview","permalink":"/docs/strapi/overview","draft":false,"unlisted":false,"editUrl":"https://github.com/Abhishek1998-cpu/Digitrix-documentation/tree/main/docs/strapi/overview.md","tags":[],"version":"current","sidebarPosition":1,"frontMatter":{"sidebar_position":1},"sidebar":"tutorialSidebar","previous":{"title":"Frontend Architecture","permalink":"/docs/architecture/frontend"},"next":{"title":"Backend Strapi Integration","permalink":"/docs/strapi/backend-integration"}},{"id":"strapi/usage-examples","title":"Strapi Usage Examples","description":"Practical examples of how to use Strapi content in your code.","source":"@site/docs/strapi/usage-examples.md","sourceDirName":"strapi","slug":"/strapi/usage-examples","permalink":"/docs/strapi/usage-examples","draft":false,"unlisted":false,"editUrl":"https://github.com/Abhishek1998-cpu/Digitrix-documentation/tree/main/docs/strapi/usage-examples.md","tags":[],"version":"current","sidebarPosition":5,"frontMatter":{"sidebar_position":5},"sidebar":"tutorialSidebar","previous":{"title":"Strapi Data Structure","permalink":"/docs/strapi/data-structure"},"next":{"title":"Strapi Webhook Configuration","permalink":"/docs/strapi/webhook-configuration"}},{"id":"strapi/webhook-configuration","title":"Strapi Webhook Configuration","description":"Learn how to configure Strapi webhooks to automatically update content in DulyPlan.","source":"@site/docs/strapi/webhook-configuration.md","sourceDirName":"strapi","slug":"/strapi/webhook-configuration","permalink":"/docs/strapi/webhook-configuration","draft":false,"unlisted":false,"editUrl":"https://github.com/Abhishek1998-cpu/Digitrix-documentation/tree/main/docs/strapi/webhook-configuration.md","tags":[],"version":"current","sidebarPosition":6,"frontMatter":{"sidebar_position":6},"sidebar":"tutorialSidebar","previous":{"title":"Strapi Usage Examples","permalink":"/docs/strapi/usage-examples"},"next":{"title":"API Overview","permalink":"/docs/api/overview"}},{"id":"user/account-management","title":"Account Management","description":"Learn how to manage your DulyPlan account and organization.","source":"@site/docs/user/account-management.md","sourceDirName":"user","slug":"/user/account-management","permalink":"/docs/user/account-management","draft":false,"unlisted":false,"editUrl":"https://github.com/Abhishek1998-cpu/Digitrix-documentation/tree/main/docs/user/account-management.md","tags":[],"version":"current","sidebarPosition":3,"frontMatter":{"sidebar_position":3},"sidebar":"tutorialSidebar","previous":{"title":"User Roles & Permissions","permalink":"/docs/user/roles-permissions"},"next":{"title":"Architecture Overview","permalink":"/docs/architecture/overview"}},{"id":"user/authentication","title":"User Authentication","description":"Learn how user authentication works in DulyPlan.","source":"@site/docs/user/authentication.md","sourceDirName":"user","slug":"/user/authentication","permalink":"/docs/user/authentication","draft":false,"unlisted":false,"editUrl":"https://github.com/Abhishek1998-cpu/Digitrix-documentation/tree/main/docs/user/authentication.md","tags":[],"version":"current","sidebarPosition":1,"frontMatter":{"sidebar_position":1},"sidebar":"tutorialSidebar","previous":{"title":"User Management Overview","permalink":"/docs/user/overview"},"next":{"title":"User Roles & Permissions","permalink":"/docs/user/roles-permissions"}},{"id":"user/overview","title":"User Management Overview","description":"Everything you need to know about users, authentication, and roles in DulyPlan.","source":"@site/docs/user/overview.md","sourceDirName":"user","slug":"/user/overview","permalink":"/docs/user/overview","draft":false,"unlisted":false,"editUrl":"https://github.com/Abhishek1998-cpu/Digitrix-documentation/tree/main/docs/user/overview.md","tags":[],"version":"current","sidebarPosition":0,"frontMatter":{"sidebar_position":0},"sidebar":"tutorialSidebar","previous":{"title":"Post Editor Features","permalink":"/docs/features/post-editor"},"next":{"title":"User Authentication","permalink":"/docs/user/authentication"}},{"id":"user/roles-permissions","title":"User Roles & Permissions","description":"Understand how user roles and permissions work in DulyPlan.","source":"@site/docs/user/roles-permissions.md","sourceDirName":"user","slug":"/user/roles-permissions","permalink":"/docs/user/roles-permissions","draft":false,"unlisted":false,"editUrl":"https://github.com/Abhishek1998-cpu/Digitrix-documentation/tree/main/docs/user/roles-permissions.md","tags":[],"version":"current","sidebarPosition":2,"frontMatter":{"sidebar_position":2},"sidebar":"tutorialSidebar","previous":{"title":"User Authentication","permalink":"/docs/user/authentication"},"next":{"title":"Account Management","permalink":"/docs/user/account-management"}}],"drafts":[],"sidebars":{"tutorialSidebar":[{"type":"category","label":"Getting Started","collapsible":true,"collapsed":true,"items":[{"type":"doc","id":"getting-started/overview"},{"type":"doc","id":"getting-started/account-setup"},{"type":"doc","id":"getting-started/dashboard-overview"},{"type":"doc","id":"getting-started/connecting-accounts"}]},{"type":"doc","id":"intro"},{"type":"category","label":"Features","collapsible":true,"collapsed":true,"items":[{"type":"doc","id":"features/social-accounts"},{"type":"doc","id":"features/creating-posts"},{"type":"doc","id":"features/scheduling"},{"type":"doc","id":"features/post-editor"}]},{"type":"category","label":"User","collapsible":true,"collapsed":true,"items":[{"type":"doc","id":"user/overview"},{"type":"doc","id":"user/authentication"},{"type":"doc","id":"user/roles-permissions"},{"type":"doc","id":"user/account-management"}]},{"type":"category","label":"Architecture","collapsible":true,"collapsed":true,"items":[{"type":"doc","id":"architecture/overview"},{"type":"doc","id":"architecture/backend"},{"type":"doc","id":"architecture/frontend"}]},{"type":"category","label":"Strapi","collapsible":true,"collapsed":true,"items":[{"type":"doc","id":"strapi/overview"},{"type":"doc","id":"strapi/backend-integration"},{"type":"doc","id":"strapi/frontend-integration"},{"type":"doc","id":"strapi/data-structure"},{"type":"doc","id":"strapi/usage-examples"},{"type":"doc","id":"strapi/webhook-configuration"}]},{"type":"category","label":"API","collapsible":true,"collapsed":true,"items":[{"type":"doc","id":"api/overview"},{"type":"doc","id":"api/authentication"},{"type":"doc","id":"api/posts"},{"type":"doc","id":"api/social-accounts"}]},{"type":"category","label":"Development","collapsible":true,"collapsed":true,"items":[{"type":"doc","id":"development/setup"},{"type":"doc","id":"development/workflow"},{"type":"doc","id":"development/code-structure"}]},{"type":"doc","id":"faq"}]}}]}},"docusaurus-plugin-content-blog":{"default":{"blogSidebarTitle":"Recent posts","blogPosts":[{"id":"welcome","metadata":{"permalink":"/blog/welcome","editUrl":"https://github.com/Abhishek1998-cpu/Digitrix-documentation/tree/main/blog/2021-08-26-welcome/index.md","source":"@site/blog/2021-08-26-welcome/index.md","title":"Welcome","description":"Docusaurus blogging features are powered by the blog plugin.","date":"2021-08-26T00:00:00.000Z","tags":[{"inline":false,"label":"Facebook","permalink":"/blog/tags/facebook","description":"Facebook tag description"},{"inline":false,"label":"Hello","permalink":"/blog/tags/hello","description":"Hello tag description"},{"inline":false,"label":"Docusaurus","permalink":"/blog/tags/docusaurus","description":"Docusaurus tag description"}],"readingTime":0.56,"hasTruncateMarker":true,"authors":[{"name":"Sébastien Lorber","title":"Docusaurus maintainer","url":"https://sebastienlorber.com","page":{"permalink":"/blog/authors/all-sebastien-lorber-articles"},"socials":{"x":"https://x.com/sebastienlorber","linkedin":"https://www.linkedin.com/in/sebastienlorber/","github":"https://github.com/slorber","newsletter":"https://thisweekinreact.com"},"imageURL":"https://github.com/slorber.png","key":"slorber"},{"name":"Yangshun Tay","title":"Ex-Meta Staff Engineer, Co-founder GreatFrontEnd","url":"https://linkedin.com/in/yangshun","page":{"permalink":"/blog/authors/yangshun"},"socials":{"x":"https://x.com/yangshunz","linkedin":"https://www.linkedin.com/in/yangshun/","github":"https://github.com/yangshun","newsletter":"https://www.greatfrontend.com"},"imageURL":"https://github.com/yangshun.png","key":"yangshun"}],"frontMatter":{"slug":"welcome","title":"Welcome","authors":["slorber","yangshun"],"tags":["facebook","hello","docusaurus"]},"unlisted":false,"nextItem":{"title":"MDX Blog Post","permalink":"/blog/mdx-blog-post"}},"content":"[Docusaurus blogging features](https://docusaurus.io/docs/blog) are powered by the [blog plugin](https://docusaurus.io/docs/api/plugins/@docusaurus/plugin-content-blog).\n\nHere are a few tips you might find useful.\n\n<!-- truncate -->\n\nSimply add Markdown files (or folders) to the `blog` directory.\n\nRegular blog authors can be added to `authors.yml`.\n\nThe blog post date can be extracted from filenames, such as:\n\n- `2019-05-30-welcome.md`\n- `2019-05-30-welcome/index.md`\n\nA blog post folder can be convenient to co-locate blog post images:\n\n![Docusaurus Plushie](./docusaurus-plushie-banner.jpeg)\n\nThe blog supports tags as well!\n\n**And if you don't want a blog**: just delete this directory, and use `blog: false` in your Docusaurus config."},{"id":"mdx-blog-post","metadata":{"permalink":"/blog/mdx-blog-post","editUrl":"https://github.com/Abhishek1998-cpu/Digitrix-documentation/tree/main/blog/2021-08-01-mdx-blog-post.mdx","source":"@site/blog/2021-08-01-mdx-blog-post.mdx","title":"MDX Blog Post","description":"Blog posts support Docusaurus Markdown features, such as MDX.","date":"2021-08-01T00:00:00.000Z","tags":[{"inline":false,"label":"Docusaurus","permalink":"/blog/tags/docusaurus","description":"Docusaurus tag description"}],"readingTime":0.27,"hasTruncateMarker":true,"authors":[{"name":"Sébastien Lorber","title":"Docusaurus maintainer","url":"https://sebastienlorber.com","page":{"permalink":"/blog/authors/all-sebastien-lorber-articles"},"socials":{"x":"https://x.com/sebastienlorber","linkedin":"https://www.linkedin.com/in/sebastienlorber/","github":"https://github.com/slorber","newsletter":"https://thisweekinreact.com"},"imageURL":"https://github.com/slorber.png","key":"slorber"}],"frontMatter":{"slug":"mdx-blog-post","title":"MDX Blog Post","authors":["slorber"],"tags":["docusaurus"]},"unlisted":false,"prevItem":{"title":"Welcome","permalink":"/blog/welcome"},"nextItem":{"title":"Long Blog Post","permalink":"/blog/long-blog-post"}},"content":"Blog posts support [Docusaurus Markdown features](https://docusaurus.io/docs/markdown-features), such as [MDX](https://mdxjs.com/).\n\n:::tip\n\nUse the power of React to create interactive blog posts.\n\n:::\n\n{/* truncate */}\n\nFor example, use JSX to create an interactive button:\n\n```js\n<button onClick={() => alert('button clicked!')}>Click me!</button>\n```\n\n<button onClick={() => alert('button clicked!')}>Click me!</button>"},{"id":"long-blog-post","metadata":{"permalink":"/blog/long-blog-post","editUrl":"https://github.com/Abhishek1998-cpu/Digitrix-documentation/tree/main/blog/2019-05-29-long-blog-post.md","source":"@site/blog/2019-05-29-long-blog-post.md","title":"Long Blog Post","description":"This is the summary of a very long blog post,","date":"2019-05-29T00:00:00.000Z","tags":[{"inline":false,"label":"Hello","permalink":"/blog/tags/hello","description":"Hello tag description"},{"inline":false,"label":"Docusaurus","permalink":"/blog/tags/docusaurus","description":"Docusaurus tag description"}],"readingTime":2.04,"hasTruncateMarker":true,"authors":[{"name":"Yangshun Tay","title":"Ex-Meta Staff Engineer, Co-founder GreatFrontEnd","url":"https://linkedin.com/in/yangshun","page":{"permalink":"/blog/authors/yangshun"},"socials":{"x":"https://x.com/yangshunz","linkedin":"https://www.linkedin.com/in/yangshun/","github":"https://github.com/yangshun","newsletter":"https://www.greatfrontend.com"},"imageURL":"https://github.com/yangshun.png","key":"yangshun"}],"frontMatter":{"slug":"long-blog-post","title":"Long Blog Post","authors":"yangshun","tags":["hello","docusaurus"]},"unlisted":false,"prevItem":{"title":"MDX Blog Post","permalink":"/blog/mdx-blog-post"},"nextItem":{"title":"First Blog Post","permalink":"/blog/first-blog-post"}},"content":"This is the summary of a very long blog post,\n\nUse a `<!--` `truncate` `-->` comment to limit blog post size in the list view.\n\n<!-- truncate -->\n\nLorem ipsum dolor sit amet, consectetur adipiscing elit. Pellentesque elementum dignissim ultricies. Fusce rhoncus ipsum tempor eros aliquam consequat. Lorem ipsum dolor sit amet\n\nLorem ipsum dolor sit amet, consectetur adipiscing elit. Pellentesque elementum dignissim ultricies. Fusce rhoncus ipsum tempor eros aliquam consequat. Lorem ipsum dolor sit amet\n\nLorem ipsum dolor sit amet, consectetur adipiscing elit. Pellentesque elementum dignissim ultricies. Fusce rhoncus ipsum tempor eros aliquam consequat. Lorem ipsum dolor sit amet\n\nLorem ipsum dolor sit amet, consectetur adipiscing elit. Pellentesque elementum dignissim ultricies. Fusce rhoncus ipsum tempor eros aliquam consequat. Lorem ipsum dolor sit amet\n\nLorem ipsum dolor sit amet, consectetur adipiscing elit. Pellentesque elementum dignissim ultricies. Fusce rhoncus ipsum tempor eros aliquam consequat. Lorem ipsum dolor sit amet\n\nLorem ipsum dolor sit amet, consectetur adipiscing elit. Pellentesque elementum dignissim ultricies. Fusce rhoncus ipsum tempor eros aliquam consequat. Lorem ipsum dolor sit amet\n\nLorem ipsum dolor sit amet, consectetur adipiscing elit. Pellentesque elementum dignissim ultricies. Fusce rhoncus ipsum tempor eros aliquam consequat. Lorem ipsum dolor sit amet\n\nLorem ipsum dolor sit amet, consectetur adipiscing elit. Pellentesque elementum dignissim ultricies. Fusce rhoncus ipsum tempor eros aliquam consequat. Lorem ipsum dolor sit amet\n\nLorem ipsum dolor sit amet, consectetur adipiscing elit. Pellentesque elementum dignissim ultricies. Fusce rhoncus ipsum tempor eros aliquam consequat. Lorem ipsum dolor sit amet\n\nLorem ipsum dolor sit amet, consectetur adipiscing elit. Pellentesque elementum dignissim ultricies. Fusce rhoncus ipsum tempor eros aliquam consequat. Lorem ipsum dolor sit amet\n\nLorem ipsum dolor sit amet, consectetur adipiscing elit. Pellentesque elementum dignissim ultricies. Fusce rhoncus ipsum tempor eros aliquam consequat. Lorem ipsum dolor sit amet\n\nLorem ipsum dolor sit amet, consectetur adipiscing elit. Pellentesque elementum dignissim ultricies. Fusce rhoncus ipsum tempor eros aliquam consequat. Lorem ipsum dolor sit amet\n\nLorem ipsum dolor sit amet, consectetur adipiscing elit. Pellentesque elementum dignissim ultricies. Fusce rhoncus ipsum tempor eros aliquam consequat. Lorem ipsum dolor sit amet\n\nLorem ipsum dolor sit amet, consectetur adipiscing elit. Pellentesque elementum dignissim ultricies. Fusce rhoncus ipsum tempor eros aliquam consequat. Lorem ipsum dolor sit amet\n\nLorem ipsum dolor sit amet, consectetur adipiscing elit. Pellentesque elementum dignissim ultricies. Fusce rhoncus ipsum tempor eros aliquam consequat. Lorem ipsum dolor sit amet\n\nLorem ipsum dolor sit amet, consectetur adipiscing elit. Pellentesque elementum dignissim ultricies. Fusce rhoncus ipsum tempor eros aliquam consequat. Lorem ipsum dolor sit amet"},{"id":"first-blog-post","metadata":{"permalink":"/blog/first-blog-post","editUrl":"https://github.com/Abhishek1998-cpu/Digitrix-documentation/tree/main/blog/2019-05-28-first-blog-post.md","source":"@site/blog/2019-05-28-first-blog-post.md","title":"First Blog Post","description":"Lorem ipsum dolor sit amet...","date":"2019-05-28T00:00:00.000Z","tags":[{"inline":false,"label":"Hola","permalink":"/blog/tags/hola","description":"Hola tag description"},{"inline":false,"label":"Docusaurus","permalink":"/blog/tags/docusaurus","description":"Docusaurus tag description"}],"readingTime":0.13,"hasTruncateMarker":true,"authors":[{"name":"Sébastien Lorber","title":"Docusaurus maintainer","url":"https://sebastienlorber.com","page":{"permalink":"/blog/authors/all-sebastien-lorber-articles"},"socials":{"x":"https://x.com/sebastienlorber","linkedin":"https://www.linkedin.com/in/sebastienlorber/","github":"https://github.com/slorber","newsletter":"https://thisweekinreact.com"},"imageURL":"https://github.com/slorber.png","key":"slorber"},{"name":"Yangshun Tay","title":"Ex-Meta Staff Engineer, Co-founder GreatFrontEnd","url":"https://linkedin.com/in/yangshun","page":{"permalink":"/blog/authors/yangshun"},"socials":{"x":"https://x.com/yangshunz","linkedin":"https://www.linkedin.com/in/yangshun/","github":"https://github.com/yangshun","newsletter":"https://www.greatfrontend.com"},"imageURL":"https://github.com/yangshun.png","key":"yangshun"}],"frontMatter":{"slug":"first-blog-post","title":"First Blog Post","authors":["slorber","yangshun"],"tags":["hola","docusaurus"]},"unlisted":false,"prevItem":{"title":"Long Blog Post","permalink":"/blog/long-blog-post"}},"content":"Lorem ipsum dolor sit amet...\n\n<!-- truncate -->\n\n...consectetur adipiscing elit. Pellentesque elementum dignissim ultricies. Fusce rhoncus ipsum tempor eros aliquam consequat. Lorem ipsum dolor sit amet"}],"blogListPaginated":[{"items":["welcome","mdx-blog-post","long-blog-post","first-blog-post"],"metadata":{"permalink":"/blog","page":1,"postsPerPage":10,"totalPages":1,"totalCount":4,"blogDescription":"Blog","blogTitle":"Blog"}}],"blogTags":{"/blog/tags/facebook":{"inline":false,"label":"Facebook","permalink":"/blog/tags/facebook","description":"Facebook tag description","items":["welcome"],"pages":[{"items":["welcome"],"metadata":{"permalink":"/blog/tags/facebook","page":1,"postsPerPage":10,"totalPages":1,"totalCount":1,"blogDescription":"Blog","blogTitle":"Blog"}}],"unlisted":false},"/blog/tags/hello":{"inline":false,"label":"Hello","permalink":"/blog/tags/hello","description":"Hello tag description","items":["welcome","long-blog-post"],"pages":[{"items":["welcome","long-blog-post"],"metadata":{"permalink":"/blog/tags/hello","page":1,"postsPerPage":10,"totalPages":1,"totalCount":2,"blogDescription":"Blog","blogTitle":"Blog"}}],"unlisted":false},"/blog/tags/docusaurus":{"inline":false,"label":"Docusaurus","permalink":"/blog/tags/docusaurus","description":"Docusaurus tag description","items":["welcome","mdx-blog-post","long-blog-post","first-blog-post"],"pages":[{"items":["welcome","mdx-blog-post","long-blog-post","first-blog-post"],"metadata":{"permalink":"/blog/tags/docusaurus","page":1,"postsPerPage":10,"totalPages":1,"totalCount":4,"blogDescription":"Blog","blogTitle":"Blog"}}],"unlisted":false},"/blog/tags/hola":{"inline":false,"label":"Hola","permalink":"/blog/tags/hola","description":"Hola tag description","items":["first-blog-post"],"pages":[{"items":["first-blog-post"],"metadata":{"permalink":"/blog/tags/hola","page":1,"postsPerPage":10,"totalPages":1,"totalCount":1,"blogDescription":"Blog","blogTitle":"Blog"}}],"unlisted":false}},"blogTagsListPath":"/blog/tags","authorsMap":{"yangshun":{"name":"Yangshun Tay","title":"Ex-Meta Staff Engineer, Co-founder GreatFrontEnd","url":"https://linkedin.com/in/yangshun","page":{"permalink":"/blog/authors/yangshun"},"socials":{"x":"https://x.com/yangshunz","linkedin":"https://www.linkedin.com/in/yangshun/","github":"https://github.com/yangshun","newsletter":"https://www.greatfrontend.com"},"imageURL":"https://github.com/yangshun.png","key":"yangshun"},"slorber":{"name":"Sébastien Lorber","title":"Docusaurus maintainer","url":"https://sebastienlorber.com","page":{"permalink":"/blog/authors/all-sebastien-lorber-articles"},"socials":{"x":"https://x.com/sebastienlorber","linkedin":"https://www.linkedin.com/in/sebastienlorber/","github":"https://github.com/slorber","newsletter":"https://thisweekinreact.com"},"imageURL":"https://github.com/slorber.png","key":"slorber"}}}},"docusaurus-plugin-content-pages":{"default":[{"type":"jsx","permalink":"/","source":"@site/src/pages/index.tsx"},{"type":"mdx","permalink":"/markdown-page","source":"@site/src/pages/markdown-page.md","title":"Markdown page example","description":"You don't need React to write simple standalone pages.","frontMatter":{"title":"Markdown page example"},"unlisted":false}]},"docusaurus-plugin-debug":{},"docusaurus-plugin-svgr":{},"docusaurus-theme-classic":{},"docusaurus-bootstrap-plugin":{},"docusaurus-mdx-fallback-plugin":{}}}